syncstart.py
syncstart-1.1.1.data/data/man/man1/syncstart.1
syncstart-1.1.1.dist-info/LICENSE.txt
syncstart-1.1.1.dist-info/METADATA
syncstart-1.1.1.dist-info/WHEEL
syncstart-1.1.1.dist-info/entry_points.txt
syncstart-1.1.1.dist-info/top_level.txt
syncstart-1.1.1.dist-info/RECORD
