Metadata-Version: 2.1
Name: syncstart
Version: 1.1.1
Summary: Calculate the cut needed at start to sync two media files.
Home-page: https://github.com/rpuntaie/syncstart
Author: Roland Puntaier
Author-email: roland.puntaier@gmail.com
License: MIT
Keywords: media file synchronization
Classifier: Development Status :: 4 - Beta
Classifier: Intended Audience :: Developers
Classifier: Intended Audience :: End Users/Desktop
Classifier: Operating System :: OS Independent
Classifier: Programming Language :: Python
Classifier: Programming Language :: Python :: 3
Classifier: License :: OSI Approved :: MIT License
Classifier: Environment :: Console
Classifier: Topic :: Utilities
Classifier: Topic :: Multimedia
Classifier: Topic :: Multimedia :: Video
Classifier: Topic :: Multimedia :: Sound/Audio
Requires-Python: >=3.6
License-File: LICENSE.txt
Requires-Dist: numpy
Requires-Dist: scipy
Requires-Dist: matplotlib
Requires-Dist: opencv-python
